eft/__init__.py
eft/crud.py
eft/database.py
eft/dataframe.py
eft/trade_date.py
eft/default/__init__.py
eft/default/timezone.py
eft-0.0.7.dist-info/METADATA
eft-0.0.7.dist-info/WHEEL
eft-0.0.7.dist-info/top_level.txt
eft-0.0.7.dist-info/RECORD
