Metadata-Version: 2.1
Name: eft
Version: 0.0.7
Summary: A efficient finance tool for personal usage
Home-page: UNKNOWN
Author: jarvixwang
Author-email: UNKNOWN
License: UNKNOWN
Platform: UNKNOWN
Requires-Dist: python-dateutil
Requires-Dist: PyMySQL
Requires-Dist: SQLAlchemy
Requires-Dist: PyHive
Requires-Dist: pandas
